alu/alu.sv
module alu(
	input logic [31:0] A,
	input logic [31:0] B,
	input logic [3:0] alu_op,
	output logic [31:0] alu_out
);

// alu_op = 0;
// alu_out = 0;

parameter ADD = 4'b0000;
parameter SUB = 4'b1000;
parameter LSL = 4'b0001;
parameter LSR = 4'b0101;
parameter ASR = 4'b1101;
parameter LTS = 4'b0010;
parameter LTU = 4'b0011;
parameter AND = 4'b0111;
parameter OR  = 4'b0110;
parameter XOR = 4'b0100;

always@(*)
case(alu_op)
	ADD: alu_out = A + B;
	SUB: alu_out = A - B;
	LSL: alu_out = A << B;
	LSR: alu_out = A >> B;
	ASR: alu_out = A >>> B;
	LTS: alu_out = ($signed(A) < $signed(B));
	LTU: alu_out = A < B;
	AND: alu_out = A & B;
	OR : alu_out = A | B;
	XOR: alu_out = A ^ B;
	default : alu_out = 0;
endcase
endmodule

alu/alu_tb.sv
module alu_tb;
	reg [31:0] A_tb;
	reg [31:0] B_tb;
	reg [3:0] op_tb;
	wire [31:0] out_tb;

	alu dut (
		.A(A_tb),
		.B(B_tb),
		.alu_op(op_tb),
		.alu_out(out_tb)
	);

	initial begin
		$dumpfile("alu.vcd");
		$dumpvars(0, alu_tb);

		A_tb = 32'b10101010101010101010101010101010;
		B_tb = 32'b11001100110011001100110011001100;		
		op_tb = 4'b0000;
		#30
		op_tb = 4'b1000;
		#30
		op_tb = 4'b0001;
		#30
		op_tb = 4'b0101;
		#30
		op_tb = 4'b1101;
		#30
		op_tb = 4'b0010;
		#30
		op_tb = 4'b0011;
		#30
		op_tb = 4'b0111;
		#30
		op_tb = 4'b0110;
		#30
		op_tb = 4'b0100;
		#50
		A_tb = 32'b00000000000000000000000001101010;
		B_tb = 32'b00000000000000000000000000000100;		
		op_tb = 4'b0000;
		#30
		op_tb = 4'b1000;
		#30
		op_tb = 4'b0001;
		#30
		op_tb = 4'b0101;
		#30
		op_tb = 4'b1101;
		#30
		op_tb = 4'b0010;
		#30
		op_tb = 4'b0011;
		#30
		op_tb = 4'b0111;
		#30
		op_tb = 4'b0110;
		#30
		op_tb = 4'b0100;
		#50
		A_tb = 32'b00000000000000001111111111111111;
		B_tb = 32'b00000001111110000000000000000100;		
		op_tb = 4'b0000;
		#30
		op_tb = 4'b1000;
		#30
		op_tb = 4'b0001;
		#30
		op_tb = 4'b0101;
		#30
		op_tb = 4'b1101;
		#30
		op_tb = 4'b0010;
		#30
		op_tb = 4'b0011;
		#30
		op_tb = 4'b0111;
		#30
		op_tb = 4'b0110;
		#30
		op_tb = 4'b0100;
		#50
		A_tb = 32'b00001111111000001111111111111111;
		B_tb = 32'b00000000000000000000001111111000;		
		op_tb = 4'b0000;
		#30
		op_tb = 4'b1000;
		#30
		op_tb = 4'b0001;
		#30
		op_tb = 4'b0101;
		#30
		op_tb = 4'b1101;
		#30
		op_tb = 4'b0010;
		#30
		op_tb = 4'b0011;
		#30
		op_tb = 4'b0111;
		#30
		op_tb = 4'b0110;
		#30
		op_tb = 4'b0100;
		#50
		$finish;
	end
endmodule

alu/alu.vcd
$date
	Thu Oct 12 22:13:41 2023
$end
$version
	Icarus Verilog
$end
$timescale
	1s
$end
$scope module alu_tb $end
$var wire 32 ! out_tb [31:0] $end
$var reg 32 " A_tb [31:0] $end
$var reg 32 # B_tb [31:0] $end
$var reg 4 $ op_tb [3:0] $end
$scope module dut $end
$var wire 32 % A [31:0] $end
$var wire 32 & B [31:0] $end
$var wire 4 ' alu_op [3:0] $end
$var parameter 4 ( ADD $end
$var parameter 4 ) AND $end
$var parameter 4 * ASR $end
$var parameter 4 + LSL $end
$var parameter 4 , LSR $end
$var parameter 4 - LTS $end
$var parameter 4 . LTU $end
$var parameter 4 / OR $end
$var parameter 4 0 SUB $end
$var parameter 4 1 XOR $end
$var reg 32 2 alu_out [31:0] $end
$upscope $end
$upscope $end
$enddefinitions $end
$comment Show the parameter values. $end
$dumpall
b100 1
b1000 0
b110 /
b11 .
b10 -
b101 ,
b1 +
b1101 *
b111 )
b0 (
$end
#0
$dumpvars
b1110111011101110111011101110110 2
b0 '
b11001100110011001100110011001100 &
b10101010101010101010101010101010 %
b0 $
b11001100110011001100110011001100 #
b10101010101010101010101010101010 "
b1110111011101110111011101110110 !
$end
#30
b11011101110111011101110111011110 !
b11011101110111011101110111011110 2
b1000 $
b1000 '
#60
b0 !
b0 2
b1 $
b1 '
#90
b101 $
b101 '
#120
b1101 $
b1101 '
#150
b1 !
b1 2
b10 $
b10 '
#180
b11 $
b11 '
#210
b10001000100010001000100010001000 !
b10001000100010001000100010001000 2
b111 $
b111 '
#240
b11101110111011101110111011101110 !
b11101110111011101110111011101110 2
b110 $
b110 '
#270
b1100110011001100110011001100110 !
b1100110011001100110011001100110 2
b100 $
b100 '
#320
b1101110 !
b1101110 2
b0 $
b0 '
b100 #
b100 &
b1101010 "
b1101010 %
#350
b1100110 !
b1100110 2
b1000 $
b1000 '
#380
b11010100000 !
b11010100000 2
b1 $
b1 '
#410
b110 !
b110 2
b101 $
b101 '
#440
b1101 $
b1101 '
#470
b0 !
b0 2
b10 $
b10 '
#500
b11 $
b11 '
#530
b111 $
b111 '
#560
b1101110 !
b1101110 2
b110 $
b110 '
#590
b100 $
b100 '
#640
b1111110010000000000000011 !
b1111110010000000000000011 2
b0 $
b0 '
b1111110000000000000000100 #
b1111110000000000000000100 &
b1111111111111111 "
b1111111111111111 %
#670
b11111110000010001111111111111011 !
b11111110000010001111111111111011 2
b1000 $
b1000 '
#700
b0 !
b0 2
b1 $
b1 '
#730
b101 $
b101 '
#760
b1101 $
b1101 '
#790
b1 !
b1 2
b10 $
b10 '
#820
b11 $
b11 '
#850
b100 !
b100 2
b111 $
b111 '
#880
b1111110001111111111111111 !
b1111110001111111111111111 2
b110 $
b110 '
#910
b1111110001111111111111011 !
b1111110001111111111111011 2
b100 $
b100 '
#960
b1111111000010000001111110111 !
b1111111000010000001111110111 2
b0 $
b0 '
b1111111000 #
b1111111000 &
b1111111000001111111111111111 "
b1111111000001111111111111111 %
#990
b1111111000001111110000000111 !
b1111111000001111110000000111 2
b1000 $
b1000 '
#1020
b0 !
b0 2
b1 $
b1 '
#1050
b101 $
b101 '
#1080
b1101 $
b1101 '
#1110
b10 $
b10 '
#1140
b11 $
b11 '
#1170
b1111111000 !
b1111111000 2
b111 $
b111 '
#1200
b1111111000001111111111111111 !
b1111111000001111111111111111 2
b110 $
b110 '
#1230
b1111111000001111110000000111 !
b1111111000001111110000000111 2
b100 $
b100 '
